ldplayer9newinstances/README.MD
ldplayer9newinstances/__init__.py
ldplayer9newinstances/requirements.txt
ldplayer9newinstances/thirdparty.json
ldplayer9newinstances-0.10.dist-info/LICENSE.rst
ldplayer9newinstances-0.10.dist-info/METADATA
ldplayer9newinstances-0.10.dist-info/WHEEL
ldplayer9newinstances-0.10.dist-info/top_level.txt
ldplayer9newinstances-0.10.dist-info/RECORD
