Metadata-Version: 2.1
Name: ldplayer9newinstances
Version: 0.10
Summary: Creates LDPlayer9 instances with independent system disk
Home-page: https://github.com/hansalemaos/ldplayer9newinstances
Author: Johannes Fischer
Author-email: aulasparticularesdealemaosp@gmail.com
License: MIT
Keywords: LDPlayer,instance
Classifier: Development Status :: 4 - Beta
Classifier: Programming Language :: Python :: 3 :: Only
Classifier: Programming Language :: Python :: 3.10
Classifier: Topic :: Software Development :: Libraries :: Python Modules
Classifier: Topic :: Utilities
License-File: LICENSE.rst
Requires-Dist: flatten-any-dict-iterable-or-whatsoever
Requires-Dist: flatten-everything
Requires-Dist: list-all-files-recursively-short
Requires-Dist: xmltodict
